ferric_crypto_lib-0.2.6.dist-info/METADATA
ferric_crypto_lib-0.2.6.dist-info/WHEEL
ferric_crypto_lib-0.2.6.dist-info/license_files/LICENSE
ferric_crypto_lib/__init__.py
ferric_crypto_lib/ferric_crypto_lib.cpython-38-x86_64-linux-gnu.so
ferric_crypto_lib-0.2.6.dist-info/RECORD
