Metadata-Version: 2.1
Name: ferric_crypto_lib
Version: 0.2.6
Classifier: Programming Language :: Rust
Classifier: Programming Language :: Python :: Implementation :: CPython
Classifier: Programming Language :: Python :: Implementation :: PyPy
License-File: LICENSE
Summary: A library for Ferric Crypto
Keywords: ferric,crypto,rust,cryptography,brute-force
Home-Page: https://gitlab.com/ferric1/ferric_crypto
Author: Tosic.Killer <emil.schutt@gmail.com>
Author-email: Tosic.Killer <emil.schutt@gmail.com>
License: MIT
Requires-Python: >=3.7
Project-URL: Source Code, https://gitlab.com/ferric1/ferric_crypto
